groceryManagement/.DS_Store
groceryManagement/__init__.py
groceryManagement/main.py
groceryManagement/utilities.py
groceryManagement/inventory_management/.DS_Store
groceryManagement/inventory_management/__init__.py
groceryManagement/inventory_management/products.py
groceryManagement/inventory_management/stock.py
groceryManagement/sales_management/.DS_Store
groceryManagement/sales_management/__init__.py
groceryManagement/sales_management/discounts.py
groceryManagement/sales_management/sales.py
grocerymanagement-0.0.1.dist-info/WHEEL
grocerymanagement-0.0.1.dist-info/METADATA
grocerymanagement-0.0.1.dist-info/RECORD
