Metadata-Version: 2.1
Name: groceryManagement
Version: 0.0.1
Summary: A project for DATA 533, UBCO
Author-email: Shiyi <shiyichen16@gmail.com>, Marina <ruomengtian@gmail.com>
Requires-Python: >=3.8
Classifier: Programming Language :: Python :: 3
Classifier: License :: OSI Approved :: MIT License
Classifier: Operating System :: OS Independent
Project-URL: Homepage, https://github.com/ubco-mds-2023-labs/project-step-3-marinatian
Project-URL: Issues, https://github.com/ubco-mds-2023-labs/project-step-3-marinatian/issues
